LICENSE
MANIFEST.in
README.md
requirements.txt
setup.cfg
setup.py
golab/__init__.py
golab.egg-info/PKG-INFO
golab.egg-info/SOURCES.txt
golab.egg-info/dependency_links.txt
golab.egg-info/requires.txt
golab.egg-info/top_level.txt