Metadata-Version: 1.1
Name: golab
Version: 0.1.2
Summary: Python client for GoLab
Home-page: https://github.com/brettlangdon/golab-python
Author: Brett Langdon
Author-email: brett@blangdon.com
License: MIT
Platform: UNKNOWN
Classifier: Intended Audience :: Developers
Classifier: Programming Language :: Python
Classifier: Programming Language :: Python :: 2.6
Classifier: Programming Language :: Python :: 2.7
Classifier: License :: OSI Approved :: MIT License
